checks_is_prime.py
setup.py
checks_is_prime.egg-info/PKG-INFO
checks_is_prime.egg-info/SOURCES.txt
checks_is_prime.egg-info/dependency_links.txt
checks_is_prime.egg-info/top_level.txt