Metadata-Version: 2.1
Name: checks-is-prime
Version: 1.0.0
Summary: Module to find whether a given number is prime number and its nearest prime. A new method game() included in version 1.0.1.
Author: Muhammad Usman
Author-email: msusman97@gmail.com
